Tareas/Tarea_3/B66963/tester.v
module tester (
    input MDC,
    input MDIO_OE,
    input MDIO_OUT,
    input [15:0] RD_DATA,
    input DATA_RDY,
    output reg MDIO_START,
    output reg [31:0] T_DATA,
    output reg clk,
    output reg reset,
    output reg MDIO_IN
);


always begin
    clk = 1'b0; #0.5;
    clk = 1'b1; #0.5;

end

initial begin
    // Prueba 1: reiniciar los registros y salidas
    reset = 1'b0; #1; #1; 
    #1; #1; #1;
    reset = 1'b1; #1; #1;
end

// Instrucciones para el generador de transacciones

initial begin
    MDIO_START = 1'b0;
    MDIO_IN = 1'b0;

    // Prueba 2: Palabra que no cumple con ST = 01 (start of frame)
    T_DATA = 32'b11101001100110100101110101101111; #1; #1; 
    #8;
    MDIO_START = 1'b1; #1; #1; // pulso MDIO_START: indica el inicio de transmisión de datos
    #160;



    // Prueba 3: lectura
    MDIO_START = 1'b0; #1; #1;
    T_DATA = 32'b01101001100110100101110101101111; 
    MDIO_START = 1'b1; #1; #1; // pulso MDIO_START: indica el inicio de transmisión de datos
    #160;
 



    MDIO_START = 1'b0; #1; #1;
    T_DATA = 32'b01011001100110100101110101101111; // Escritura
    MDIO_START = 1'b1; #1; #1; // pulso MDIO_START: indica el inicio de transmisión de datos
    #160;

end


initial begin
    #175;
    MDIO_IN = 1'b0; #1; #1; #1; #1; 
    MDIO_IN = 1'b1; #1; #1; #1; #1;
    MDIO_IN = 1'b0; #1; #1; #1; #1;
    MDIO_IN = 1'b1; #1; #1; #1; #1;
    MDIO_IN = 1'b1; #1; #1; #1; #1;
    MDIO_IN = 1'b0; #1; #1; #1; #1;
    MDIO_IN = 1'b1; #1; #1; #1; #1;
    MDIO_IN = 1'b0; #1; #1; #1; #1;
    MDIO_IN = 1'b0; #1; #1; #1; #1; 
    MDIO_IN = 1'b0; #1; #1; #1; #1;
    MDIO_IN = 1'b1; #1; #1; #1; #1;
    MDIO_IN = 1'b1; #1; #1; #1; #1;
    MDIO_IN = 1'b0; #1; #1; #1; #1;
    MDIO_IN = 1'b1; #1; #1; #1; #1;
    MDIO_IN = 1'b0; #1; #1; #1; #1;
    MDIO_IN = 1'b1; #1; #1; #1; #1;
    MDIO_IN = 1'b0; #1; #1; #1; #1;
    #610;
    $finish;
end

endmodule

Tareas/Tarea_3/Maquina_Estado2.v
module maquina_estado  (input clk,
                        input reset, 
                        input MDIO_START,
                        input MDIO_IN, 
                        input [31:0]T_DATA, 
                        output reg MDC, 
                        output reg MDIO_OUT, 
                        output reg MDIO_OE, 
                        output reg [15:0]RD_DATA,
                        output reg DATA_RDY);

    // Los estados de la Maquina de estados
    // Estado ST        --> 000
    // Estado OP        --> 001
    // Estado PHYADR    --> 010
    // Estado REGADR    --> 011
    // Estado TA        --> 100
    // Estado DATA lec  --> 101
    // Estado DATA esc  --> 110

    reg [2:0] state;
    reg [2:0] nxt_state; 
    reg [4:0] count;

    reg [1:0] ST;
    reg [1:0] OP;
    reg [4:0] PHYADR;
    reg [4:0] REGADR;
    reg [1:0] TA;
    reg [15:0] DATA_read;
    reg [15:0] DATA_write;

    reg [31:0] q;
    reg [15:0] temp;
    reg [5:0] counter;



    // Clock Divider
    always @ (posedge(clk))
    begin
        if (~reset) MDC <= 0;
        else MDC <= !MDC;
    end

    // Si reset no es igual a 1, pone las salidas en 0.
    always @(posedge clk) begin
        if (~reset) begin
            RD_DATA <= 16'h0000;
            MDIO_OE <= 1'b0;
            MDIO_OUT <= 1'b0;
            DATA_RDY <= 1'b0;
            temp = 16'h0000;
        end

    end

    always @(posedge MDC) begin
        

        ST = T_DATA [31:30];
        OP = T_DATA [29:28];
        PHYADR = T_DATA [27:23];
        REGADR = T_DATA [22:18];
        TA = T_DATA [17:16];

        nxt_state = 3'b000;

        q <= 32'h0000_0000;

        if (reset == 1) begin

            counter <= 6'b000000;
            q <= T_DATA;

            

            $display("valor de state hola = %b", state);

            if (MDIO_START) begin

                state = nxt_state;

                counter <= counter+1;
                MDIO_OUT <= q[0];
                q<=q>>1;

                $display("valor de ST = %b", ST);
                $display("valor de OP = %b", OP);
                $display("valor de state = %b", state);

                case (state)
                    
                    //Primer Estado ST
                    3'b000 : begin if (ST == 2'b01) begin
                                nxt_state = 3'b001;
                                $display ("Estado 1");
                                $display("valor de state = %b ", state);
                            end else if (ST != 2'b01) begin
                                nxt_state = 3'b000;
                            end
                    end

                    // Segundo Estado OP
                    3'b001 : begin  if (OP == 2'b01 || OP == 2'b10) begin
                                nxt_state = 3'b010;
                                $display ("Estado 2");
                            end else begin
                                nxt_state = 3'b000;
                            end
                    end
                
                    // Tercer Estado PHYADR
                    3'b010 : nxt_state = 3'b011;


                    // Cuarto Estado REGADR
                    3'b011 : nxt_state = 3'b100;


                    // Quinto Estado TA y se divide en Escritura o Lectura
                    3'b100 : begin if (OP == 2'b01 ) begin
                            // Caso para escribir
                                nxt_state = 3'b101;
                            end else if (OP == 2'b10) begin
                            // Caso para lectura
                                nxt_state = 3'b110;
                            end
                    end
                            

                    // Sexto Estado, Escritura
                    3'b101 : begin
                            $display ("Estado 6");
                            DATA_write = T_DATA [15:0];
                            MDIO_OE <= 1'b1;

                            if (counter > 5'b11111) begin
                                MDIO_OE <= 1'b0;
                            end 
                        end
                

                    // Septimo Estado, Lectura
                    3'b110 : begin
                            DATA_read = T_DATA [15:0];
                            MDIO_OE <= 1'b1;
                            $display ("Estado 7");
                            if (counter >= 5'b01111) begin
                                MDIO_OE <= 1'b0;
                            end

                            if (counter >= 5'b01111 && counter < 5'b11111)begin
                                    DATA_RDY <=1'b1;
                            end

                            // Se hace la carga de paralelo a serie
                            temp <= temp << 1;
                            temp[0] <= MDIO_IN;

                            if (MDIO_OE == 1'b0 && DATA_RDY == 1) begin
                               RD_DATA <= temp;
                            end
                            
                            if (count >= 31) begin
                            // transaccion se ha realizado exitosamente.
                                MDIO_OE <= 1'b0;                
                            end
                        end
                    default : state = 3'bxxx; 
                endcase
            end
        end    
    end
endmodule

Tareas/Tarea_3/testbench.v
`include "Maquina_Estado2.v"
`include "tester.v"

module testbench();

    wire MDC;
    wire MDIO_OE;
    wire MDIO_OUT;
    wire [15:0] RD_DATA;
    wire DATA_RDY;
    wire MDIO_START;
    wire [31:0] T_DATA;
    wire clk;
    wire reset;
    wire MDIO_IN;

    maquina_estado dut (.MDC(MDC), 
                    .MDIO_OE(MDIO_OE), 
                    .MDIO_OUT(MDIO_OUT), 
                    .RD_DATA(RD_DATA), 
                    .DATA_RDY(DATA_RDY), 
                    .MDIO_START(MDIO_START), 
                    .T_DATA(T_DATA), 
                    .clk(clk), 
                    .reset(reset), 
                    .MDIO_IN(MDIO_IN));

    tester test (.MDC(MDC), 
                    .MDIO_OE(MDIO_OE), 
                    .MDIO_OUT(MDIO_OUT), 
                    .RD_DATA(RD_DATA), 
                    .DATA_RDY(DATA_RDY), 
                    .MDIO_START(MDIO_START), 
                    .T_DATA(T_DATA), 
                    .clk(clk), 
                    .reset(reset), 
                    .MDIO_IN(MDIO_IN));

    initial begin
        $dumpfile("tb.vcd");
        $dumpvars(-1, testbench);
        //$monitor("clk = %b, MDC = %b, MDIO_START = %b", clk, MDC, MDIO_START);
    end


endmodule

Tareas/Tarea_3/tb.vcd
$date
	Tue Oct 11 14:41:51 2022
$end
$version
	Icarus Verilog
$end
$timescale
	1s
$end
$scope module testbench $end
$var wire 1 ! reset $end
$var wire 1 " clk $end
$var wire 32 # T_DATA [31:0] $end
$var wire 16 $ RD_DATA [15:0] $end
$var wire 1 % MDIO_START $end
$var wire 1 & MDIO_OUT $end
$var wire 1 ' MDIO_OE $end
$var wire 1 ( MDIO_IN $end
$var wire 1 ) MDC $end
$var wire 1 * DATA_RDY $end
$scope module dut $end
$var wire 1 ! reset $end
$var wire 1 " clk $end
$var wire 32 + T_DATA [31:0] $end
$var wire 1 % MDIO_START $end
$var wire 1 ( MDIO_IN $end
$var reg 1 * DATA_RDY $end
$var reg 16 , DATA_read [15:0] $end
$var reg 16 - DATA_write [15:0] $end
$var reg 1 ) MDC $end
$var reg 1 ' MDIO_OE $end
$var reg 1 & MDIO_OUT $end
$var reg 2 . OP [1:0] $end
$var reg 5 / PHYADR [4:0] $end
$var reg 16 0 RD_DATA [15:0] $end
$var reg 5 1 REGADR [4:0] $end
$var reg 2 2 ST [1:0] $end
$var reg 2 3 TA [1:0] $end
$var reg 5 4 count [4:0] $end
$var reg 6 5 counter [5:0] $end
$var reg 3 6 nxt_state [2:0] $end
$var reg 32 7 q [31:0] $end
$var reg 3 8 state [2:0] $end
$var reg 16 9 temp [15:0] $end
$upscope $end
$scope module test $end
$var wire 1 * DATA_RDY $end
$var wire 1 ) MDC $end
$var wire 1 ' MDIO_OE $end
$var wire 1 & MDIO_OUT $end
$var wire 16 : RD_DATA [15:0] $end
$var reg 1 ( MDIO_IN $end
$var reg 1 % MDIO_START $end
$var reg 32 ; T_DATA [31:0] $end
$var reg 1 " clk $end
$var reg 1 ! reset $end
$upscope $end
$upscope $end
$enddefinitions $end
#0
$dumpvars
b11101001100110100101110101101111 ;
bx :
bx 9
bx 8
bx 7
bx 6
bx 5
bx 4
bx 3
bx 2
bx 1
bx 0
bx /
bx .
bx -
bx ,
b11101001100110100101110101101111 +
x*
x)
0(
x'
x&
0%
bx $
b11101001100110100101110101101111 #
0"
0!
$end
#1
0)
0*
0&
0'
b0 $
b0 0
b0 :
b0 9
1"
#2
0"
#3
1"
#4
0"
#5
b0 5
b11101001100110100101110101101111 7
b0 6
b10 3
b110 1
b10011 /
b10 .
b11 2
1)
1!
1"
#6
0"
#7
0)
1"
#8
0"
#9
b11101001100110100101110101101111 7
1)
1"
#10
0"
1%
#11
0)
1"
#12
0"
#13
1&
b1 5
b1110100110011010010111010110111 7
b0 8
1)
1"
#14
0"
#15
0)
1"
#16
0"
#17
b10 5
b111010011001101001011101011011 7
1)
1"
#18
0"
#19
0)
1"
#20
0"
#21
b11 5
b11101001100110100101110101101 7
1)
1"
#22
0"
#23
0)
1"
#24
0"
#25
b100 5
b1110100110011010010111010110 7
1)
1"
#26
0"
#27
0)
1"
#28
0"
#29
0&
b101 5
b111010011001101001011101011 7
1)
1"
#30
0"
#31
0)
1"
#32
0"
#33
1&
b110 5
b11101001100110100101110101 7
1)
1"
#34
0"
#35
0)
1"
#36
0"
#37
b111 5
b1110100110011010010111010 7
1)
1"
#38
0"
#39
0)
1"
#40
0"
#41
0&
b1000 5
b111010011001101001011101 7
1)
1"
#42
0"
#43
0)
1"
#44
0"
#45
1&
b1001 5
b11101001100110100101110 7
1)
1"
#46
0"
#47
0)
1"
#48
0"
#49
0&
b1010 5
b1110100110011010010111 7
1)
1"
#50
0"
#51
0)
1"
#52
0"
#53
1&
b1011 5
b111010011001101001011 7
1)
1"
#54
0"
#55
0)
1"
#56
0"
#57
b1100 5
b11101001100110100101 7
1)
1"
#58
0"
#59
0)
1"
#60
0"
#61
b1101 5
b1110100110011010010 7
1)
1"
#62
0"
#63
0)
1"
#64
0"
#65
0&
b1110 5
b111010011001101001 7
1)
1"
#66
0"
#67
0)
1"
#68
0"
#69
1&
b1111 5
b11101001100110100 7
1)
1"
#70
0"
#71
0)
1"
#72
0"
#73
0&
b10000 5
b1110100110011010 7
1)
1"
#74
0"
#75
0)
1"
#76
0"
#77
b10001 5
b111010011001101 7
1)
1"
#78
0"
#79
0)
1"
#80
0"
#81
1&
b10010 5
b11101001100110 7
1)
1"
#82
0"
#83
0)
1"
#84
0"
#85
0&
b10011 5
b1110100110011 7
1)
1"
#86
0"
#87
0)
1"
#88
0"
#89
1&
b10100 5
b111010011001 7
1)
1"
#90
0"
#91
0)
1"
#92
0"
#93
b10101 5
b11101001100 7
1)
1"
#94
0"
#95
0)
1"
#96
0"
#97
0&
b10110 5
b1110100110 7
1)
1"
#98
0"
#99
0)
1"
#100
0"
#101
b10111 5
b111010011 7
1)
1"
#102
0"
#103
0)
1"
#104
0"
#105
1&
b11000 5
b11101001 7
1)
1"
#106
0"
#107
0)
1"
#108
0"
#109
b11001 5
b1110100 7
1)
1"
#110
0"
#111
0)
1"
#112
0"
#113
0&
b11010 5
b111010 7
1)
1"
#114
0"
#115
0)
1"
#116
0"
#117
b11011 5
b11101 7
1)
1"
#118
0"
#119
0)
1"
#120
0"
#121
1&
b11100 5
b1110 7
1)
1"
#122
0"
#123
0)
1"
#124
0"
#125
0&
b11101 5
b111 7
1)
1"
#126
0"
#127
0)
1"
#128
0"
#129
1&
b11110 5
b11 7
1)
1"
#130
0"
#131
0)
1"
#132
0"
#133
b11111 5
b1 7
1)
1"
#134
0"
#135
0)
1"
#136
0"
#137
b100000 5
b0 7
1)
1"
#138
0"
#139
0)
1"
#140
0"
#141
0&
b0 7
b100001 5
1)
1"
#142
0"
#143
0)
1"
#144
0"
#145
b0 7
b100010 5
1)
1"
#146
0"
#147
0)
1"
#148
0"
#149
b0 7
b100011 5
1)
1"
#150
0"
#151
0)
1"
#152
0"
#153
b0 7
b100100 5
1)
1"
#154
0"
#155
0)
1"
#156
0"
#157
b0 7
b100101 5
1)
1"
#158
0"
#159
0)
1"
#160
0"
#161
b0 7
b100110 5
1)
1"
#162
0"
#163
0)
1"
#164
0"
#165
b0 7
b100111 5
1)
1"
#166
0"
#167
0)
1"
#168
0"
#169
b0 7
b101000 5
1)
1"
#170
0"
#171
0)
1"
#172
0"
0%
#173
b11101001100110100101110101101111 7
b0 5
1)
1"
#174
0"
1%
b1101001100110100101110101101111 #
b1101001100110100101110101101111 +
b1101001100110100101110101101111 ;
#175
0)
1"
#176
0"
#177
1&
b1 5
b1110100110011010010111010110111 7
b1 6
b1 2
1)
1"
#178
0"
#179
0)
1"
1(
#180
0"
#181
b10 5
b111010011001101001011101011011 7
b1 6
1)
1"
#182
0"
#183
0)
1"
0(
#184
0"
#185
b11 5
b11101001100110100101110101101 7
b1 6
1)
1"
#186
0"
#187
0)
1"
1(
#188
0"
#189
b100 5
b1110100110011010010111010110 7
b1 6
1)
1"
#190
0"
#191
0)
1"
#192
0"
#193
0&
b101 5
b111010011001101001011101011 7
b1 6
1)
1"
#194
0"
#195
0)
1"
0(
#196
0"
#197
1&
b110 5
b11101001100110100101110101 7
b1 6
1)
1"
#198
0"
#199
0)
1"
1(
#200
0"
#201
b111 5
b1110100110011010010111010 7
b1 6
1)
1"
#202
0"
#203
0)
1"
0(
#204
0"
#205
0&
b1000 5
b111010011001101001011101 7
b1 6
1)
1"
#206
0"
#207
0)
1"
#208
0"
#209
1&
b1001 5
b11101001100110100101110 7
b1 6
1)
1"
#210
0"
#211
0)
1"
#212
0"
#213
0&
b1010 5
b1110100110011010010111 7
b1 6
1)
1"
#214
0"
#215
0)
1"
1(
#216
0"
#217
1&
b1011 5
b111010011001101001011 7
b1 6
1)
1"
#218
0"
#219
0)
1"
#220
0"
#221
b1100 5
b11101001100110100101 7
b1 6
1)
1"
#222
0"
#223
0)
1"
0(
#224
0"
#225
b1101 5
b1110100110011010010 7
b1 6
1)
1"
#226
0"
#227
0)
1"
1(
#228
0"
#229
0&
b1110 5
b111010011001101001 7
b1 6
1)
1"
#230
0"
#231
0)
1"
0(
#232
0"
#233
1&
b1111 5
b11101001100110100 7
b1 6
1)
1"
#234
0"
#235
0)
1"
1(
#236
0"
#237
0&
b10000 5
b1110100110011010 7
b1 6
1)
1"
#238
0"
#239
0)
1"
0(
#240
0"
#241
b10001 5
b111010011001101 7
b1 6
1)
1"
#242
0"
#243
0)
1"
#244
0"
#245
1&
b10010 5
b11101001100110 7
b1 6
1)
1"
#246
0"
#247
0)
1"
#248
0"
#249
0&
b10011 5
b1110100110011 7
b1 6
1)
1"
#250
0"
#251
0)
1"
#252
0"
#253
1&
b10100 5
b111010011001 7
b1 6
1)
1"
#254
0"
#255
0)
1"
#256
0"
#257
b10101 5
b11101001100 7
b1 6
1)
1"
#258
0"
#259
0)
1"
#260
0"
#261
0&
b10110 5
b1110100110 7
b1 6
1)
1"
#262
0"
#263
0)
1"
#264
0"
#265
b10111 5
b111010011 7
b1 6
1)
1"
#266
0"
#267
0)
1"
#268
0"
#269
1&
b11000 5
b11101001 7
b1 6
1)
1"
#270
0"
#271
0)
1"
#272
0"
#273
b11001 5
b1110100 7
b1 6
1)
1"
#274
0"
#275
0)
1"
#276
0"
#277
0&
b11010 5
b111010 7
b1 6
1)
1"
#278
0"
#279
0)
1"
#280
0"
#281
b11011 5
b11101 7
b1 6
1)
1"
#282
0"
#283
0)
1"
#284
0"
#285
1&
b11100 5
b1110 7
b1 6
1)
1"
#286
0"
#287
0)
1"
#288
0"
#289
0&
b11101 5
b111 7
b1 6
1)
1"
#290
0"
#291
0)
1"
#292
0"
#293
1&
b11110 5
b11 7
b1 6
1)
1"
#294
0"
#295
0)
1"
#296
0"
#297
b11111 5
b1 7
b1 6
1)
1"
#298
0"
#299
0)
1"
#300
0"
#301
b100000 5
b0 7
b1 6
1)
1"
#302
0"
#303
0)
1"
#304
0"
#305
0&
b0 7
b100001 5
b1 6
1)
1"
#306
0"
#307
0)
1"
#308
0"
#309
b0 7
b100010 5
b1 6
1)
1"
#310
0"
#311
0)
1"
#312
0"
#313
b0 7
b100011 5
b1 6
1)
1"
#314
0"
#315
0)
1"
#316
0"
#317
b0 7
b100100 5
b1 6
1)
1"
#318
0"
#319
0)
1"
#320
0"
#321
b0 7
b100101 5
b1 6
1)
1"
#322
0"
#323
0)
1"
#324
0"
#325
b0 7
b100110 5
b1 6
1)
1"
#326
0"
#327
0)
1"
#328
0"
#329
b0 7
b100111 5
b1 6
1)
1"
#330
0"
#331
0)
1"
#332
0"
#333
b0 7
b101000 5
b1 6
1)
1"
#334
0"
#335
0)
1"
#336
0"
0%
#337
b1101001100110100101110101101111 7
b0 5
b0 6
1)
1"
#338
0"
1%
b1011001100110100101110101101111 #
b1011001100110100101110101101111 +
b1011001100110100101110101101111 ;
#339
0)
1"
#340
0"
#341
1&
b1 5
b110100110011010010111010110111 7
b1 6
b1 .
1)
1"
#342
0"
#343
0)
1"
#344
0"
#345
b10 5
b11010011001101001011101011011 7
b1 6
1)
1"
#346
0"
#347
0)
1"
#348
0"
#349
b11 5
b1101001100110100101110101101 7
b1 6
1)
1"
#350
0"
#351
0)
1"
#352
0"
#353
b100 5
b110100110011010010111010110 7
b1 6
1)
1"
#354
0"
#355
0)
1"
#356
0"
#357
0&
b101 5
b11010011001101001011101011 7
b1 6
1)
1"
#358
0"
#359
0)
1"
#360
0"
#361
1&
b110 5
b1101001100110100101110101 7
b1 6
1)
1"
#362
0"
#363
0)
1"
#364
0"
#365
b111 5
b110100110011010010111010 7
b1 6
1)
1"
#366
0"
#367
0)
1"
#368
0"
#369
0&
b1000 5
b11010011001101001011101 7
b1 6
1)
1"
#370
0"
#371
0)
1"
#372
0"
#373
1&
b1001 5
b1101001100110100101110 7
b1 6
1)
1"
#374
0"
#375
0)
1"
#376
0"
#377
0&
b1010 5
b110100110011010010111 7
b1 6
1)
1"
#378
0"
#379
0)
1"
#380
0"
#381
1&
b1011 5
b11010011001101001011 7
b1 6
1)
1"
#382
0"
#383
0)
1"
#384
0"
#385
b1100 5
b1101001100110100101 7
b1 6
1)
1"
#386
0"
#387
0)
1"
#388
0"
#389
b1101 5
b110100110011010010 7
b1 6
1)
1"
#390
0"
#391
0)
1"
#392
0"
#393
0&
b1110 5
b11010011001101001 7
b1 6
1)
1"
#394
0"
#395
0)
1"
#396
0"
#397
1&
b1111 5
b1101001100110100 7
b1 6
1)
1"
#398
0"
#399
0)
1"
#400
0"
#401
0&
b10000 5
b110100110011010 7
b1 6
1)
1"
#402
0"
#403
0)
1"
#404
0"
#405
b10001 5
b11010011001101 7
b1 6
1)
1"
#406
0"
#407
0)
1"
#408
0"
#409
1&
b10010 5
b1101001100110 7
b1 6
1)
1"
#410
0"
#411
0)
1"
#412
0"
#413
0&
b10011 5
b110100110011 7
b1 6
1)
1"
#414
0"
#415
0)
1"
#416
0"
#417
1&
b10100 5
b11010011001 7
b1 6
1)
1"
#418
0"
#419
0)
1"
#420
0"
#421
b10101 5
b1101001100 7
b1 6
1)
1"
#422
0"
#423
0)
1"
#424
0"
#425
0&
b10110 5
b110100110 7
b1 6
1)
1"
#426
0"
#427
0)
1"
#428
0"
#429
b10111 5
b11010011 7
b1 6
1)
1"
#430
0"
#431
0)
1"
#432
0"
#433
1&
b11000 5
b1101001 7
b1 6
1)
1"
#434
0"
#435
0)
1"
#436
0"
#437
b11001 5
b110100 7
b1 6
1)
1"
#438
0"
#439
0)
1"
#440
0"
#441
0&
b11010 5
b11010 7
b1 6
1)
1"
#442
0"
#443
0)
1"
#444
0"
#445
b11011 5
b1101 7
b1 6
1)
1"
#446
0"
#447
0)
1"
#448
0"
#449
1&
b11100 5
b110 7
b1 6
1)
1"
#450
0"
#451
0)
1"
#452
0"
#453
0&
b11101 5
b11 7
b1 6
1)
1"
#454
0"
#455
0)
1"
#456
0"
#457
1&
b11110 5
b1 7
b1 6
1)
1"
#458
0"
#459
0)
1"
#460
0"
#461
b11111 5
b0 7
b1 6
1)
1"
#462
0"
#463
0)
1"
#464
0"
#465
0&
b0 7
b100000 5
b1 6
1)
1"
#466
0"
#467
0)
1"
#468
0"
#469
b0 7
b100001 5
b1 6
1)
1"
#470
0"
#471
0)
1"
#472
0"
#473
b0 7
b100010 5
b1 6
1)
1"
#474
0"
#475
0)
1"
#476
0"
#477
b0 7
b100011 5
b1 6
1)
1"
#478
0"
#479
0)
1"
#480
0"
#481
b0 7
b100100 5
b1 6
1)
1"
#482
0"
#483
0)
1"
#484
0"
#485
b0 7
b100101 5
b1 6
1)
1"
#486
0"
#487
0)
1"
#488
0"
#489
b0 7
b100110 5
b1 6
1)
1"
#490
0"
#491
0)
1"
#492
0"
#493
b0 7
b100111 5
b1 6
1)
1"
#494
0"
#495
0)
1"
#496
0"
#497
b0 7
b101000 5
b1 6
1)
1"
#498
0"
#499
0)
1"
#500
0"
#501
b0 7
b101001 5
b1 6
1)
1"
#502
0"
#503
0)
1"
#504
0"
#505
b0 7
b101010 5
b1 6
1)
1"
#506
0"
#507
0)
1"
#508
0"
#509
b0 7
b101011 5
b1 6
1)
1"
#510
0"
#511
0)
1"
#512
0"
#513
b0 7
b101100 5
b1 6
1)
1"
#514
0"
#515
0)
1"
#516
0"
#517
b0 7
b101101 5
b1 6
1)
1"
#518
0"
#519
0)
1"
#520
0"
#521
b0 7
b101110 5
b1 6
1)
1"
#522
0"
#523
0)
1"
#524
0"
#525
b0 7
b101111 5
b1 6
1)
1"
#526
0"
#527
0)
1"
#528
0"
#529
b0 7
b110000 5
b1 6
1)
1"
#530
0"
#531
0)
1"
#532
0"
#533
b0 7
b110001 5
b1 6
1)
1"
#534
0"
#535
0)
1"
#536
0"
#537
b0 7
b110010 5
b1 6
1)
1"
#538
0"
#539
0)
1"
#540
0"
#541
b0 7
b110011 5
b1 6
1)
1"
#542
0"
#543
0)
1"
#544
0"
#545
b0 7
b110100 5
b1 6
1)
1"
#546
0"
#547
0)
1"
#548
0"
#549
b0 7
b110101 5
b1 6
1)
1"
#550
0"
#551
0)
1"
#552
0"
#553
b0 7
b110110 5
b1 6
1)
1"
#554
0"
#555
0)
1"
#556
0"
#557
b0 7
b110111 5
b1 6
1)
1"
#558
0"
#559
0)
1"
#560
0"
#561
b0 7
b111000 5
b1 6
1)
1"
#562
0"
#563
0)
1"
#564
0"
#565
b0 7
b111001 5
b1 6
1)
1"
#566
0"
#567
0)
1"
#568
0"
#569
b0 7
b111010 5
b1 6
1)
1"
#570
0"
#571
0)
1"
#572
0"
#573
b0 7
b111011 5
b1 6
1)
1"
#574
0"
#575
0)
1"
#576
0"
#577
b0 7
b111100 5
b1 6
1)
1"
#578
0"
#579
0)
1"
#580
0"
#581
b0 7
b111101 5
b1 6
1)
1"
#582
0"
#583
0)
1"
#584
0"
#585
b0 7
b111110 5
b1 6
1)
1"
#586
0"
#587
0)
1"
#588
0"
#589
b0 7
b111111 5
b1 6
1)
1"
#590
0"
#591
0)
1"
#592
0"
#593
b0 7
b0 5
b1 6
1)
1"
#594
0"
#595
0)
1"
#596
0"
#597
b1 5
b0 7
b1 6
1)
1"
#598
0"
#599
0)
1"
#600
0"
#601
b0 7
b10 5
b1 6
1)
1"
#602
0"
#603
0)
1"
#604
0"
#605
b0 7
b11 5
b1 6
1)
1"
#606
0"
#607
0)
1"
#608
0"
#609
b0 7
b100 5
b1 6
1)
1"
#610
0"
#611
0)
1"
#612
0"
#613
b0 7
b101 5
b1 6
1)
1"
#614
0"
#615
0)
1"
#616
0"
#617
b0 7
b110 5
b1 6
1)
1"
#618
0"
#619
0)
1"
#620
0"
#621
b0 7
b111 5
b1 6
1)
1"
#622
0"
#623
0)
1"
#624
0"
#625
b0 7
b1000 5
b1 6
1)
1"
#626
0"
#627
0)
1"
#628
0"
#629
b0 7
b1001 5
b1 6
1)
1"
#630
0"
#631
0)
1"
#632
0"
#633
b0 7
b1010 5
b1 6
1)
1"
#634
0"
#635
0)
1"
#636
0"
#637
b0 7
b1011 5
b1 6
1)
1"
#638
0"
#639
0)
1"
#640
0"
#641
b0 7
b1100 5
b1 6
1)
1"
#642
0"
#643
0)
1"
#644
0"
#645
b0 7
b1101 5
b1 6
1)
1"
#646
0"
#647
0)
1"
#648
0"
#649
b0 7
b1110 5
b1 6
1)
1"
#650
0"
#651
0)
1"
#652
0"
#653
b0 7
b1111 5
b1 6
1)
1"
#654
0"
#655
0)
1"
#656
0"
#657
b0 7
b10000 5
b1 6
1)
1"
#658
0"
#659
0)
1"
#660
0"
#661
b0 7
b10001 5
b1 6
1)
1"
#662
0"
#663
0)
1"
#664
0"
#665
b0 7
b10010 5
b1 6
1)
1"
#666
0"
#667
0)
1"
#668
0"
#669
b0 7
b10011 5
b1 6
1)
1"
#670
0"
#671
0)
1"
#672
0"
#673
b0 7
b10100 5
b1 6
1)
1"
#674
0"
#675
0)
1"
#676
0"
#677
b0 7
b10101 5
b1 6
1)
1"
#678
0"
#679
0)
1"
#680
0"
#681
b0 7
b10110 5
b1 6
1)
1"
#682
0"
#683
0)
1"
#684
0"
#685
b0 7
b10111 5
b1 6
1)
1"
#686
0"
#687
0)
1"
#688
0"
#689
b0 7
b11000 5
b1 6
1)
1"
#690
0"
#691
0)
1"
#692
0"
#693
b0 7
b11001 5
b1 6
1)
1"
#694
0"
#695
0)
1"
#696
0"
#697
b0 7
b11010 5
b1 6
1)
1"
#698
0"
#699
0)
1"
#700
0"
#701
b0 7
b11011 5
b1 6
1)
1"
#702
0"
#703
0)
1"
#704
0"
#705
b0 7
b11100 5
b1 6
1)
1"
#706
0"
#707
0)
1"
#708
0"
#709
b0 7
b11101 5
b1 6
1)
1"
#710
0"
#711
0)
1"
#712
0"
#713
b0 7
b11110 5
b1 6
1)
1"
#714
0"
#715
0)
1"
#716
0"
#717
b0 7
b11111 5
b1 6
1)
1"
#718
0"
#719
0)
1"
#720
0"
#721
b0 7
b100000 5
b1 6
1)
1"
#722
0"
#723
0)
1"
#724
0"
#725
b0 7
b100001 5
b1 6
1)
1"
#726
0"
#727
0)
1"
#728
0"
#729
b0 7
b100010 5
b1 6
1)
1"
#730
0"
#731
0)
1"
#732
0"
#733
b0 7
b100011 5
b1 6
1)
1"
#734
0"
#735
0)
1"
#736
0"
#737
b0 7
b100100 5
b1 6
1)
1"
#738
0"
#739
0)
1"
#740
0"
#741
b0 7
b100101 5
b1 6
1)
1"
#742
0"
#743
0)
1"
#744
0"
#745
b0 7
b100110 5
b1 6
1)
1"
#746
0"
#747
0)
1"
#748
0"
#749
b0 7
b100111 5
b1 6
1)
1"
#750
0"
#751
0)
1"
#752
0"
#753
b0 7
b101000 5
b1 6
1)
1"
#754
0"
#755
0)
1"
#756
0"
#757
b0 7
b101001 5
b1 6
1)
1"
#758
0"
#759
0)
1"
#760
0"
#761
b0 7
b101010 5
b1 6
1)
1"
#762
0"
#763
0)
1"
#764
0"
#765
b0 7
b101011 5
b1 6
1)
1"
#766
0"
#767
0)
1"
#768
0"
#769
b0 7
b101100 5
b1 6
1)
1"
#770
0"
#771
0)
1"
#772
0"
#773
b0 7
b101101 5
b1 6
1)
1"
#774
0"
#775
0)
1"
#776
0"
#777
b0 7
b101110 5
b1 6
1)
1"
#778
0"
#779
0)
1"
#780
0"
#781
b0 7
b101111 5
b1 6
1)
1"
#782
0"
#783
0)
1"
#784
0"
#785
b0 7
b110000 5
b1 6
1)
1"
#786
0"
#787
0)
1"
#788
0"
#789
b0 7
b110001 5
b1 6
1)
1"
#790
0"
#791
0)
1"
#792
0"
#793
b0 7
b110010 5
b1 6
1)
1"
#794
0"
#795
0)
1"
#796
0"
#797
b0 7
b110011 5
b1 6
1)
1"
#798
0"
#799
0)
1"
#800
0"
#801
b0 7
b110100 5
b1 6
1)
1"
#802
0"
#803
0)
1"
#804
0"
#805
b0 7
b110101 5
b1 6
1)
1"
#806
0"
#807
0)
1"
#808
0"
#809
b0 7
b110110 5
b1 6
1)
1"
#810
0"
#811
0)
1"
#812
0"
#813
b0 7
b110111 5
b1 6
1)
1"
#814
0"
#815
0)
1"
#816
0"
#817
b0 7
b111000 5
b1 6
1)
1"
#818
0"
#819
0)
1"
#820
0"
#821
b0 7
b111001 5
b1 6
1)
1"
#822
0"
#823
0)
1"
#824
0"
#825
b0 7
b111010 5
b1 6
1)
1"
#826
0"
#827
0)
1"
#828
0"
#829
b0 7
b111011 5
b1 6
1)
1"
#830
0"
#831
0)
1"
#832
0"
#833
b0 7
b111100 5
b1 6
1)
1"
#834
0"
#835
0)
1"
#836
0"
#837
b0 7
b111101 5
b1 6
1)
1"
#838
0"
#839
0)
1"
#840
0"
#841
b0 7
b111110 5
b1 6
1)
1"
#842
0"
#843
0)
1"
