Tareas/Tarea_1/tester.v
`timescale 1ns/1ns


module tester (
    output reg clk, // se asigna el clk como una salida 
    output reg [3:0]D, // se asigna el D como una salida de 4 bits
    output reg [1:0]modo, // se asigna el modo como una salida como salida 2 bits 
    output reg enb, // se asigna el enb como una salida 
    input rco, // se asigna el rco como una entrada 
    input [3:0] Q // se asigna el Q como una entrada de 4 bits 
);

// Creacion del reloj
always begin
    #5 clk =! clk;  // Cada 10 unidades de tiempo vuelve el flanco positivo del reloj
end


/*
    En el siguiente inicial, se inicializan las entradas del contador de 4 bits, tambien se ejecutan las pruebas con el fin de poner 
    en funcionamiento el contador. Cada 10ns representa un cilco positivo del reloj.
*/
/*initial begin  

    $display("Caso Modo 00, Cuenta Ascendente");
    $display("ENB    MODO   D       Q    rco");
    clk = 0; 
    enb = 1'b1; 
    modo = 2'b11;
    D[3:0] = 4'b0000;

    #5; #5;
    
    modo = 2'b00;  // Define el modo cuenta ascendente 
    #5; #5;
    #5; #5;
    #5; #5;
    #5; #5;
    #5; #5;
    #5; #5;
    #5; #5;
    #5; #5;
    #5; #5;
    #5; #5;
    #5; #5;
    #5; #5;
    #5; #5;
    #5; #5;
    #5; #5;
    #5; #5;
    #5; #5;

    
    // Vuelve a inicializar las variables para hacer el cambio de modo
    

    $display("Caso Modo 01, Cuenta Descendente");
    $display("ENB    MODO   D       Q    rco");
    enb = 1'b1; 
    modo = 2'b11;
    D[3:0] = 4'b1111;

    #5; #5;

    modo = 2'b01; // Define el modo cuenta descendente 
    
    #5; #5;
    #5; #5;
    #5; #5;
    #5; #5;
    #5; #5;
    #5; #5;
    #5; #5;
    #5; #5;
    #5; #5;
    #5; #5;
    #5; #5;
    #5; #5;
    #5; #5;
    #5; #5;
    #5; #5;
    #5; #5;
    #5; #5;

    // Vuelve a inicializar las variables para hacer el cambio de modo

    $display("Caso Modo 10, Cuenta Descendente de 3 en 3");
    $display("ENB    MODO   D       Q    rco");
    enb = 1'b1; 
    modo = 2'b11;
    D[3:0] = 4'b1111;

    #5; #5;


    modo = 2'b10; // Define el modo cuenta descendente de 3 en 3 
    #5; #5;
    #5; #5;
    #5; #5;
    #5; #5;
    #5; #5;
    #5; #5;
    #5; #5;


    // Vuelve a inicializar las variables para hacer el cambio de modo
    $display("Caso Modo 11, Cuenta Paralela");
    $display("ENB    MODO   D       Q    rco");
    enb = 1'b1; 
    modo = 2'b11;
    D[3:0] = 4'bXXXX;

    #5; #5;


    modo = 2'b11; // Define el modo cuenta ascendente carga en paralelo
    D[3:0] = 1'b1; 
    #5; #5;
    D[3:0] = 4'b0000; 
    #5; #5;
    D[3:0] = 4'b0001;
    #5; #5;
    D[3:0] = 4'b0010;
    #5; #5;
    D[3:0] = 4'b0011;
    #5; #5;
    D[3:0] = 4'b0100;
    #5; #5;
    D[3:0] = 4'b0101;
    #5; #5;
    D[3:0] = 4'b0110;
    #5; #5;
    D[3:0] = 4'b0111;
    #5; #5;
    D[3:0] = 4'b1000;
    #5; #5;
    D[3:0] = 4'b1001;
    #5; #5;
    D[3:0] = 4'b1010;
    #5; #5;
    D[3:0] = 4'b1011;
    #5; #5;
    D[3:0] = 4'b1100;
    #5; #5;
    D[3:0] = 4'b1101;
    #5; #5;
    D[3:0] = 4'b1110;
    #5; #5;
    D[3:0] = 4'b1111;
    #5; #5;
    D[3:0] = 4'b0000;


    #20 $finish;  
end  */

endmodule

module tester_16Bits(
                    output reg clk,
                    output reg [1:0]modo,
                    output reg enb,
                    output reg [15:0]D2,
                    input rco1,
                    input rco2,
                    input rco3,
                    input rco4,
                    input [15:0] Q2);


     
    // Creacion del reloj
    always begin
    #5 clk =! clk;  // Cada 10 unidades de tiempo vuelve el flanco positivo del reloj
    end


    //   En el siguiente inicial, se inicializan las entradas del contador de 4 bits, tambien se ejecutan las pruebas con el fin de poner 
    // en funcionamiento el contador. Cada 10ns representa un cilco positivo del reloj.
    initial begin



        $display("Caso Modo 00, Cuenta ascendente");
        $display("ENB    MODO           D                    Q           rco");
        clk = 1'b0; 
        enb = 1'b1; 
        modo = 2'b11;
        D2[15:0] = 16'b0000_0000_0000_1111;
    
        
        #5; #5;
        
        
        modo = 2'b00; // Define el modo cuenta ascendente 
        #5; #5;
        #5; #5;
        #5; #5;
        #5; #5;
        #5; #5;
        #5; #5;
        #5; #5;
        #5; #5;
        #5; #5;
        #5; #5;
        #5; #5;
        #5; #5;
        #5; #5;
        #5; #5;
        #5; #5;
        #5; #5;
        #5; #5;
        #5; #5;
        #5; #5;
        #5; #5;
        #5; #5;
        #5; #5;
        #5; #5;
        #5; #5;
        #5; #5;
        #5; #5;
        #5; #5;
        #5; #5;
        #5; #5;
        #5; #5;
        #5; #5;
        #5; #5;
        #5; #5;
        #5; #5;
        #5; #5;
        #5; #5;
        #5; #5;
        #5; #5;
        #5; #5;
        #5; #5;
        #5; #5;
        #5; #5;
        #5; #5;
        #5; #5;
        #5; #5;
        #5; #5;
        #5; #5;
        #5; #5;


  


        // Vuelve a inicializar las variables para hacer el cambio de modo
        $display("Caso Modo 01, Cuenta Descendente");
        $display("ENB    MODO           D                    Q           rco");
        clk = 0; 
        enb = 1'b1; 
        modo = 2'b11;
        D2[15:0] = 16'hffff;
    
        #5; #5;
        
        
        modo = 2'b01;  // Define el modo cuenta descendente 
        #5; #5;
        #5; #5;
        #5; #5;
        #5; #5;
        #5; #5;
        #5; #5;
        #5; #5;
        #5; #5;
        #5; #5;
        #5; #5;
        #5; #5;
        #5; #5;
        #5; #5;
        #5; #5;
        #5; #5;
        #5; #5;
        #5; #5;
        #5; #5;
        #5; #5;
        #5; #5;
        #5; #5;
        #5; #5;
        #5; #5;
        #5; #5;
        #5; #5;
        #5; #5;
        #5; #5;
        #5; #5;
        #5; #5;
        #5; #5;
        #5; #5;
        #5; #5;
        #5; #5;
        #5; #5;
        #5; #5;
        #5; #5;
        #5; #5;
        #5; #5;
        #5; #5;
        #5; #5;
        #5; #5;
        #5; #5;
        #5; #5;
        #5; #5;
        #5; #5;
        #5; #5;
        #5; #5;
        #5; #5;



        // Vuelve a inicializar las variables para hacer el cambio de modo
        $display("Caso Modo 10, Cuenta Descendente de 3 en 3");
        $display("ENB    MODO           D                    Q           rco");
        clk = 0; 
        enb = 1'b1; 
        modo = 2'b11;
        D2[15:0] = 16'hffff;

        #5; #5;
        
        
        modo = 2'b10;  // Define el modo cuenta descendente 3 en 3 
        #5; #5;
        #5; #5;
        #5; #5;
        #5; #5;
        #5; #5;
        #5; #5;
        #5; #5;
        #5; #5;
        #5; #5;
        #5; #5;
        #5; #5;
        #5; #5;
        #5; #5;
        #5; #5;
        #5; #5;
        #5; #5;
        #5; #5;
        #5; #5;
        #5; #5;
        #5; #5;
        #5; #5;
        #5; #5;
        #5; #5;
        #5; #5;
        #5; #5;
        #5; #5;
        #5; #5;
        #5; #5;
        #5; #5;
        #5; #5;
        #5; #5;
        #5; #5;
        #5; #5;
        #5; #5;
        #5; #5;
        #5; #5;
        #5; #5;
        #5; #5;
        #5; #5;
        #5; #5;
        #5; #5;
        #5; #5;
        #5; #5;
        #5; #5;
        #5; #5;
        #5; #5;
        #5; #5;
        #5; #5;



        // Vuelve a inicializar las variables para hacer el cambio de modo
        $display("Caso Modo 11, Cuenta Paralela");
        $display("ENB    MODO           D                    Q           rco");
        clk = 0; 
        enb = 1'b1; 
        modo = 2'b11;
        D2[15:0] = 16'bXXXX_XXXX_XXXX_XXXX;
    
        #5; #5;

        modo = 2'b11;  // Define el modo carga en paralelo
        D2[15:0] = 16'h0001;  
        #5; #5;
        D2[15:0] += 1'b1;  
        #5; #5;
        D2[15:0] += 1'b1;  
        #5; #5;
        D2[15:0] += 1'b1;  
        #5; #5;
        D2[15:0] += 1'b1;  
        #5; #5;
        D2[15:0] += 1'b1;  
        #5; #5;
        D2[15:0] += 1'b1;  
        #5; #5;
        D2[15:0] += 1'b1;  
        #5; #5;
        D2[15:0] += 1'b1;  
        #5; #5;
        D2[15:0] += 1'b1;  
        #5; #5;
        D2[15:0] += 1'b1;  
        #5; #5;
        D2[15:0] += 1'b1;  
        #5; #5;
        D2[15:0] += 1'b1;  
        #5; #5;
        D2[15:0] += 1'b1;  
        #5; #5;
        D2[15:0] += 1'b1;  
        #5; #5;
        D2[15:0] += 1'b1;  
        #5; #5;
        D2[15:0] += 1'b1;  
        #5; #5;
        D2[15:0] += 1'b1;  
        #5; #5;
        D2[15:0] += 1'b1;  
        #5; #5;
        D2[15:0] += 1'b1;  
        #5; #5;
        D2[15:0] += 1'b1;  
        #5; #5;
        D2[15:0] += 1'b1;  
        #5; #5;
        D2[15:0] += 1'b1;  
        #5; #5;
        D2[15:0] += 1'b1;  
        #5; #5;
        D2[15:0] += 1'b1;  
        #5; #5;
  

        #20 $finish; 
    end

endmodule

Tareas/Tarea_1/flipflop.v
/* flip flop tipo D de n bits disparado por flanco
   creciente de clk con entrada de habilitacion enb.
   */
module DFF_nbits_enb #(parameter BITS = 1)
(
    input clk,
    input enb,
    input [BITS-1:0] d,
    output reg [BITS-1:0] q
);

always @(posedge clk) begin
    if (enb == 1'b1)
        q <= d;
end

endmodule

Tareas/Tarea_1/Counter.v
`include "flipflop.v"

module counter (input clk,  //se asigna el clk como una entrada
                input enb,  // se asigna el enb como una entrada
                input [1:0]modo,      // se asigna en modo como una entrada de 2 bits  
                input [3:0]D,      // se asigna el D como una entrada de 4 bits       
                output [3:0] Q,  // se asigna el Q como una salida de 4 bits
                output rco);    // se asigna el rco (Ripple-Carry Out) como una salida
  
    reg [3:0] D_In; // Registro de 4 bits para la salida Q
    reg D_Out; // Registro de 1 bit para la salida rco


    /*
        El siguiete codigo es para poder seleccionar el modo en que se quiere usar el contador
        ya que modo es de 2 bits, se tiene 4 posibilidades de seleccion (00,01,10,11), entonces se 
        dividen por casos, el caso 00 es una cuenta ascendente, para el caso 01 es una cuenta descendente,
        para el caso 10 es una cuenta descendente de 3 en 3 y para el caso 11 es una carga en paralelo.
    */
  
  always @* begin  
    case ({modo[1:0]})

    //  Caso con el modo 00, cuenta ascendente

        2'b00 : begin   if (enb == 1) begin  // Este if se asegura que el codigo funcione siempre que el enb este en 1
                                        D_In = Q + 1;
                                        if (Q == 4'b1111) begin  // Este if se encarga de activar el RCO siempre que haya uno de lo contrario va a estar en 0.
                                        D_Out = 1;
                                        end else begin
                                        D_Out = 0;
                                        end 
                                    end   
                            end     
        
        //  Caso con el modo 01, cuenta Descendente

        2'b01 : begin   if (enb == 1) begin
                                        D_In = Q - 1;
                                        if (Q == 4'b0000) begin  // Este if se encarga de activar el RCO siempre que haya uno de lo contrario va a estar en 0.
                                        D_Out = 1;
                                        end else begin
                                        D_Out = 0;
                                        end  
                                    end
                        end 
          
        //  Caso con el modo 10, cuenta descendente de 3 en 3

        2'b10 : begin   if (enb == 1) begin
                                D_In = Q - 3;
                                if (Q == 4'b0000 || Q == 4'b0001 || Q == 4'b0010) begin //Este if activa el RCO, cuando la resta -3 tiene un rco
                                  D_Out = 1;
                              end else begin
                                  D_Out = 0;
                              end   
                          end
                    end    

        //  Caso con el modo 11

        2'b11 : begin  D_In = D;   // Carga en paralelo.
                if (D == 4'b0000) begin
                    D_Out = 1;    
                end else begin
                    D_Out = 0;
                end
                

        end 
        
        default : begin D_In = D_In; end // Si no hay cambio de modo, se mantiene.

    endcase
  end

  // se intancia 2 flipflops, uno para la salida y otro para el RCO, de manera que el programa funcione siempre que 
  // el enable este en alto.
  DFF_nbits_enb #(.BITS(4)) DFF_4bits(.clk(clk), .enb(enb), .d(D_In[3:0]), .q(Q[3:0])); // Registro de 4 bits para Q[3:0]
  DFF_nbits_enb DFF_1bit(.clk(clk), .enb(enb), .d(D_Out), .q(rco)); // Registro de 1 bits para RCO
 


endmodule  

/*
En el siguiente modulo, se instancia 4 veces el contador de 4 bits, con el fin de construir un contador de 16 bits, de manera que 
se asigna un reloj nuevo a cada uno de los contadores, entonces para el contador 1 este va a tener el reloj normal, para el contador 2, este reloj se
va a activar siempre cuando se active el rco del contador 1, para el reloj del contador 3 se activa cuando el rco del contador 2 se activa y 
para el reloj del contador 4 se activa cuando el rco del contador 3 se activa.
*/

module Counter16( input clk,
                  input enb,
                  input [1:0]modo,      
                  input [15:0]D2,              
                  output [15:0]Q2,
                  output rco1,
                  output rco2,
                  output rco3,
                  output rco4);
    
    wire clk2;
    wire clk3;
    wire clk4;
    wire modo_11;

    assign modo_11 = (modo == 2'b11); 
    assign clk2 = clk && modo_11 || rco1 && !modo_11; // Usa el reloj o usa como reloj el RCO, esto para el contador 2
    assign clk3 = clk && modo_11 || rco2 && !modo_11; // Usa el reloj o usa como reloj el RCO, esto para el contador 3
    assign clk4 = clk && modo_11 || rco3 && !modo_11; // Usa el reloj o usa como reloj el RCO, esto para el contador 4


    //En la siguientes lineas de codigo es donde se instancia el 4 contadores de 4 bits.
    counter contador1(.clk(clk), .enb(enb), .modo(modo[1:0]), .D(D2[3:0]), .Q(Q2[3:0]),.rco(rco1));
    counter contador2(.clk(clk2), .enb(enb), .modo(modo[1:0]), .D(D2[7:4]), .Q(Q2[7:4]),.rco(rco2));
    counter contador3(.clk(clk3), .enb(enb), .modo(modo[1:0]), .D(D2[11:8]), .Q(Q2[11:8]),.rco(rco3));    
    counter contador4(.clk(clk4), .enb(enb), .modo(modo[1:0]), .D(D2[15:12]), .Q(Q2[15:12]),.rco(rco4));


endmodule

Tareas/Tarea_1/tb_Counter.v
`include "Counter.v"
`include "tester.v"




//  Banco de pruebas para el contador de 4 bits


module tb_Counter; // Modulo para el contador de 4 Bits

    wire clk;                     
    wire [3:0]D;                     
    wire [3:0] Q;
    wire [1:0] modo;
    wire enb;
    wire rco;             
 

    // se instancia el contador de 4 bits que se encuentra en el archivo Counter.v
    tester prueba (.clk(clk), .D(D), .Q (Q), .modo (modo), .enb (enb), .rco(rco));
    // se instancia el probador de 4 bits que se encuentra en el archivo tester.v
    counter DUT4 (.clk(clk), .D(D), .Q (Q), .modo (modo), .enb (enb), .rco(rco)); 


  //  Para imprimir en consola los valores de enb, modo, D2, Q2. rco1
 
    always @(posedge clk) begin
    $display(" %b     %b   %b    %b     %b", enb, modo, D, Q, rco);
    end




 //   Para visualizar el gtkwave del contador de 4 bits

    initial begin
        $dumpfile("tb.vcd");
        $dumpvars;
    end

endmodule 



 // Banco de pruebas para el contador de 16 bits


module tb_Counter_16Bit; // Modulo para el contador de 16 Bits

    wire clk;                     
    wire [15:0]D2;                    
    wire [1:0] modo;
    wire [15:0] Q2;
    wire enb;
    wire rco1;
    wire rco2;
    wire rco3;
    wire rco4; 



    // se instancia el contador de 16 bits que se encuentra en el archivo Counter.v
    Counter16 DUT16 (.clk(clk),.D2(D2),.Q2(Q2),.modo(modo),.enb(enb),.rco1(rco1),.rco2(rco2),.rco3(rco3),.rco4(rco4)); 

    // se instancia el Probador de 16 bits que se encuentra en el archivo tester.v
    tester_16Bits prueba16 (.clk(clk), .D2(D2), .Q2(Q2), .modo(modo), .enb(enb),.rco1(rco1),.rco2(rco2),.rco3(rco3),.rco4(rco4));


    //Para imprimir en consola los valores de enb, modo, D2, Q2. rco1

    always @(posedge clk) begin
    $display(" %b     %b      %b    %b     %b ", enb, modo, D2, Q2, rco1);
    end



   // Para visualizar el gtkwave del contador de 16 bits

    initial begin
        $dumpfile("tb.vcd");
        $dumpvars;
    end


endmodule

Tareas/Tarea_1/tb.vcd
$date
	Wed Oct  5 13:23:14 2022
$end
$version
	Icarus Verilog
$end
$timescale
	1ns
$end
$scope module tb_Counter $end
$var wire 1 ! rco $end
$var wire 2 " modo [1:0] $end
$var wire 1 # enb $end
$var wire 1 $ clk $end
$var wire 4 % Q [3:0] $end
$var wire 4 & D [3:0] $end
$scope module DUT4 $end
$var wire 1 ! rco $end
$var wire 2 ' modo [1:0] $end
$var wire 1 # enb $end
$var wire 1 $ clk $end
$var wire 4 ( Q [3:0] $end
$var wire 4 ) D [3:0] $end
$var reg 4 * D_In [3:0] $end
$var reg 1 + D_Out $end
$scope module DFF_1bit $end
$var wire 1 + d $end
$var wire 1 # enb $end
$var wire 1 $ clk $end
$var reg 1 ! q $end
$upscope $end
$scope module DFF_4bits $end
$var wire 4 , d [3:0] $end
$var wire 1 # enb $end
$var wire 1 $ clk $end
$var reg 4 - q [3:0] $end
$upscope $end
$upscope $end
$scope module prueba $end
$var wire 4 . Q [3:0] $end
$var wire 1 ! rco $end
$var reg 4 / D [3:0] $end
$var reg 1 $ clk $end
$var reg 1 # enb $end
$var reg 2 0 modo [1:0] $end
$upscope $end
$upscope $end
$scope module tb_Counter_16Bit $end
$var wire 1 1 rco4 $end
$var wire 1 2 rco3 $end
$var wire 1 3 rco2 $end
$var wire 1 4 rco1 $end
$var wire 2 5 modo [1:0] $end
$var wire 1 6 enb $end
$var wire 1 7 clk $end
$var wire 16 8 Q2 [15:0] $end
$var wire 16 9 D2 [15:0] $end
$scope module DUT16 $end
$var wire 1 : clk2 $end
$var wire 1 ; clk3 $end
$var wire 1 < clk4 $end
$var wire 1 1 rco4 $end
$var wire 1 2 rco3 $end
$var wire 1 3 rco2 $end
$var wire 1 4 rco1 $end
$var wire 1 = modo_11 $end
$var wire 2 > modo [1:0] $end
$var wire 1 6 enb $end
$var wire 1 7 clk $end
$var wire 16 ? Q2 [15:0] $end
$var wire 16 @ D2 [15:0] $end
$scope module contador1 $end
$var wire 4 A D [3:0] $end
$var wire 1 4 rco $end
$var wire 2 B modo [1:0] $end
$var wire 1 6 enb $end
$var wire 1 7 clk $end
$var wire 4 C Q [3:0] $end
$var reg 4 D D_In [3:0] $end
$var reg 1 E D_Out $end
$scope module DFF_1bit $end
$var wire 1 E d $end
$var wire 1 6 enb $end
$var wire 1 7 clk $end
$var reg 1 4 q $end
$upscope $end
$scope module DFF_4bits $end
$var wire 4 F d [3:0] $end
$var wire 1 6 enb $end
$var wire 1 7 clk $end
$var reg 4 G q [3:0] $end
$upscope $end
$upscope $end
$scope module contador2 $end
$var wire 4 H D [3:0] $end
$var wire 1 : clk $end
$var wire 1 3 rco $end
$var wire 2 I modo [1:0] $end
$var wire 1 6 enb $end
$var wire 4 J Q [3:0] $end
$var reg 4 K D_In [3:0] $end
$var reg 1 L D_Out $end
$scope module DFF_1bit $end
$var wire 1 : clk $end
$var wire 1 L d $end
$var wire 1 6 enb $end
$var reg 1 3 q $end
$upscope $end
$scope module DFF_4bits $end
$var wire 1 : clk $end
$var wire 4 M d [3:0] $end
$var wire 1 6 enb $end
$var reg 4 N q [3:0] $end
$upscope $end
$upscope $end
$scope module contador3 $end
$var wire 4 O D [3:0] $end
$var wire 1 ; clk $end
$var wire 1 2 rco $end
$var wire 2 P modo [1:0] $end
$var wire 1 6 enb $end
$var wire 4 Q Q [3:0] $end
$var reg 4 R D_In [3:0] $end
$var reg 1 S D_Out $end
$scope module DFF_1bit $end
$var wire 1 ; clk $end
$var wire 1 S d $end
$var wire 1 6 enb $end
$var reg 1 2 q $end
$upscope $end
$scope module DFF_4bits $end
$var wire 1 ; clk $end
$var wire 4 T d [3:0] $end
$var wire 1 6 enb $end
$var reg 4 U q [3:0] $end
$upscope $end
$upscope $end
$scope module contador4 $end
$var wire 4 V D [3:0] $end
$var wire 1 < clk $end
$var wire 1 1 rco $end
$var wire 2 W modo [1:0] $end
$var wire 1 6 enb $end
$var wire 4 X Q [3:0] $end
$var reg 4 Y D_In [3:0] $end
$var reg 1 Z D_Out $end
$scope module DFF_1bit $end
$var wire 1 < clk $end
$var wire 1 Z d $end
$var wire 1 6 enb $end
$var reg 1 1 q $end
$upscope $end
$scope module DFF_4bits $end
$var wire 1 < clk $end
$var wire 4 [ d [3:0] $end
$var wire 1 6 enb $end
$var reg 4 \ q [3:0] $end
$upscope $end
$upscope $end
$upscope $end
$scope module prueba16 $end
$var wire 16 ] Q2 [15:0] $end
$var wire 1 4 rco1 $end
$var wire 1 3 rco2 $end
$var wire 1 2 rco3 $end
$var wire 1 1 rco4 $end
$var reg 16 ^ D2 [15:0] $end
$var reg 1 7 clk $end
$var reg 1 6 enb $end
$var reg 2 _ modo [1:0] $end
$upscope $end
$upscope $end
$scope module tb_Counter $end
$scope module DUT4 $end
$scope module DFF_1bit $end
$upscope $end
$scope module DFF_4bits $end
$upscope $end
$upscope $end
$scope module prueba $end
$upscope $end
$upscope $end
$scope module tb_Counter_16Bit $end
$scope module DUT16 $end
$scope module contador1 $end
$scope module DFF_1bit $end
$upscope $end
$scope module DFF_4bits $end
$upscope $end
$upscope $end
$scope module contador2 $end
$scope module DFF_1bit $end
$upscope $end
$scope module DFF_4bits $end
$upscope $end
$upscope $end
$scope module contador3 $end
$scope module DFF_1bit $end
$upscope $end
$scope module DFF_4bits $end
$upscope $end
$upscope $end
$scope module contador4 $end
$scope module DFF_1bit $end
$upscope $end
$scope module DFF_4bits $end
$upscope $end
$upscope $end
$upscope $end
$scope module prueba16 $end
$upscope $end
$upscope $end
$enddefinitions $end
#0
$dumpvars
b11 _
b1111 ^
bx ]
bx \
b0 [
1Z
b0 Y
bx X
b11 W
b0 V
bx U
b0 T
1S
b0 R
bx Q
b11 P
b0 O
bx N
b0 M
1L
b0 K
bx J
b11 I
b0 H
bx G
b1111 F
0E
b1111 D
bx C
b11 B
b1111 A
b1111 @
bx ?
b11 >
1=
0<
0;
0:
b1111 9
bx 8
07
16
b11 5
x4
x3
x2
x1
bx 0
bx /
bx .
bx -
bx ,
x+
bx *
bx )
bx (
bx '
bx &
bx %
x$
x#
bx "
x!
$end
#5
b0 X
b0 \
11
b0 Q
b0 U
12
b0 J
b0 N
13
b1111 8
b1111 ?
b1111 ]
b1111 C
b1111 G
04
1<
1;
1:
17
#10
0:
1E
b0 D
b0 F
0L
b1 K
b1 M
0S
b1 R
b1 T
0Z
b1 Y
b1 [
0=
b0 5
b0 >
b0 B
b0 I
b0 P
b0 W
b0 _
07
#15
0;
b10 K
b10 M
03
b1 J
b1 N
1:
0E
b1 D
b1 F
14
b10000 8
b10000 ?
b10000 ]
b0 C
b0 G
17
#20
07
#25
0:
b10 D
b10 F
b10001 8
b10001 ?
b10001 ]
b1 C
b1 G
04
17
#30
07
#35
b11 D
b11 F
b10010 8
b10010 ?
b10010 ]
b10 C
b10 G
17
#40
07
#45
b100 D
b100 F
b10011 8
b10011 ?
b10011 ]
b11 C
b11 G
17
#50
07
#55
b101 D
b101 F
b10100 8
b10100 ?
b10100 ]
b100 C
b100 G
17
#60
07
#65
b110 D
b110 F
b10101 8
b10101 ?
b10101 ]
b101 C
b101 G
17
#70
07
#75
b111 D
b111 F
b10110 8
b10110 ?
b10110 ]
b110 C
b110 G
17
#80
07
#85
b1000 D
b1000 F
b10111 8
b10111 ?
b10111 ]
b111 C
b111 G
17
#90
07
#95
b1001 D
b1001 F
b11000 8
b11000 ?
b11000 ]
b1000 C
b1000 G
17
#100
07
#105
b1010 D
b1010 F
b11001 8
b11001 ?
b11001 ]
b1001 C
b1001 G
17
#110
07
#115
b1011 D
b1011 F
b11010 8
b11010 ?
b11010 ]
b1010 C
b1010 G
17
#120
07
#125
b1100 D
b1100 F
b11011 8
b11011 ?
b11011 ]
b1011 C
b1011 G
17
#130
07
#135
b1101 D
b1101 F
b11100 8
b11100 ?
b11100 ]
b1100 C
b1100 G
17
#140
07
#145
b1110 D
b1110 F
b11101 8
b11101 ?
b11101 ]
b1101 C
b1101 G
17
#150
07
#155
b1111 D
b1111 F
b11110 8
b11110 ?
b11110 ]
b1110 C
b1110 G
17
#160
07
#165
1E
b0 D
b0 F
b11111 8
b11111 ?
b11111 ]
b1111 C
b1111 G
17
#170
07
#175
b11 K
b11 M
b10 J
b10 N
1:
0E
b1 D
b1 F
14
b100000 8
b100000 ?
b100000 ]
b0 C
b0 G
17
#180
07
#185
0:
b10 D
b10 F
b100001 8
b100001 ?
b100001 ]
b1 C
b1 G
04
17
#190
07
#195
b11 D
b11 F
b100010 8
b100010 ?
b100010 ]
b10 C
b10 G
17
#200
07
#205
b100 D
b100 F
b100011 8
b100011 ?
b100011 ]
b11 C
b11 G
17
#210
07
#215
b101 D
b101 F
b100100 8
b100100 ?
b100100 ]
b100 C
b100 G
17
#220
07
#225
b110 D
b110 F
b100101 8
b100101 ?
b100101 ]
b101 C
b101 G
17
#230
07
#235
b111 D
b111 F
b100110 8
b100110 ?
b100110 ]
b110 C
b110 G
17
#240
07
#245
b1000 D
b1000 F
b100111 8
b100111 ?
b100111 ]
b111 C
b111 G
17
#250
07
#255
b1001 D
b1001 F
b101000 8
b101000 ?
b101000 ]
b1000 C
b1000 G
17
#260
07
#265
b1010 D
b1010 F
b101001 8
b101001 ?
b101001 ]
b1001 C
b1001 G
17
#270
07
#275
b1011 D
b1011 F
b101010 8
b101010 ?
b101010 ]
b1010 C
b1010 G
17
#280
07
#285
b1100 D
b1100 F
b101011 8
b101011 ?
b101011 ]
b1011 C
b1011 G
17
#290
07
#295
b1101 D
b1101 F
b101100 8
b101100 ?
b101100 ]
b1100 C
b1100 G
17
#300
07
#305
b1110 D
b1110 F
b101101 8
b101101 ?
b101101 ]
b1101 C
b1101 G
17
#310
07
#315
b1111 D
b1111 F
b101110 8
b101110 ?
b101110 ]
b1110 C
b1110 G
17
#320
07
#325
1E
b0 D
b0 F
b101111 8
b101111 ?
b101111 ]
b1111 C
b1111 G
17
#330
07
#335
b100 K
b100 M
b11 J
b11 N
1:
0E
b1 D
b1 F
14
b110000 8
b110000 ?
b110000 ]
b0 C
b0 G
17
#340
07
#345
0:
b10 D
b10 F
b110001 8
b110001 ?
b110001 ]
b1 C
b1 G
04
17
#350
07
#355
b11 D
b11 F
b110010 8
b110010 ?
b110010 ]
b10 C
b10 G
17
#360
07
#365
b100 D
b100 F
b110011 8
b110011 ?
b110011 ]
b11 C
b11 G
17
#370
07
#375
b101 D
b101 F
b110100 8
b110100 ?
b110100 ]
b100 C
b100 G
17
#380
07
#385
b110 D
b110 F
b110101 8
b110101 ?
b110101 ]
b101 C
b101 G
17
#390
07
#395
b111 D
b111 F
b110110 8
b110110 ?
b110110 ]
b110 C
b110 G
17
#400
07
#405
b1000 D
b1000 F
b110111 8
b110111 ?
b110111 ]
b111 C
b111 G
17
#410
07
#415
b1001 D
b1001 F
b111000 8
b111000 ?
b111000 ]
b1000 C
b1000 G
17
#420
07
#425
b1010 D
b1010 F
b111001 8
b111001 ?
b111001 ]
b1001 C
b1001 G
17
#430
07
#435
b1011 D
b1011 F
b111010 8
b111010 ?
b111010 ]
b1010 C
b1010 G
17
#440
07
#445
b1100 D
b1100 F
b111011 8
b111011 ?
b111011 ]
b1011 C
b1011 G
17
#450
07
#455
b1101 D
b1101 F
b111100 8
b111100 ?
b111100 ]
b1100 C
b1100 G
17
#460
07
#465
b1110 D
b1110 F
b111101 8
b111101 ?
b111101 ]
b1101 C
b1101 G
17
#470
07
#475
b1111 D
b1111 F
b111110 8
b111110 ?
b111110 ]
b1110 C
b1110 G
17
#480
07
#485
1E
b0 D
b0 F
b111111 8
b111111 ?
b111111 ]
b1111 C
b1111 G
17
#490
0<
b1111 V
b1111 O
b1111 H
0E
b1111 D
b1111 F
0L
b1111 K
b1111 M
0S
b1111 R
b1111 T
0Z
b1111 Y
b1111 [
b1111111111111111 9
b1111111111111111 @
b1111111111111111 ^
1=
b11 5
b11 >
b11 B
b11 I
b11 P
b11 W
b11 _
07
#495
01
b1111 X
b1111 \
02
b1111 Q
b1111 U
b1111111111111111 8
b1111111111111111 ?
b1111111111111111 ]
b1111 J
b1111 N
1<
1;
1:
17
#500
0<
0;
0:
b1110 D
b1110 F
b1110 K
b1110 M
b1110 R
b1110 T
b1110 Y
b1110 [
0=
b1 5
b1 >
b1 B
b1 I
b1 P
b1 W
b1 _
07
#505
b1101 D
b1101 F
b1111111111111110 8
b1111111111111110 ?
b1111111111111110 ]
b1110 C
b1110 G
17
#510
07
#515
b1100 D
b1100 F
b1111111111111101 8
b1111111111111101 ?
b1111111111111101 ]
b1101 C
b1101 G
17
#520
07
#525
b1011 D
b1011 F
b1111111111111100 8
b1111111111111100 ?
b1111111111111100 ]
b1100 C
b1100 G
17
#530
07
#535
b1010 D
b1010 F
b1111111111111011 8
b1111111111111011 ?
b1111111111111011 ]
b1011 C
b1011 G
17
#540
07
#545
b1001 D
b1001 F
b1111111111111010 8
b1111111111111010 ?
b1111111111111010 ]
b1010 C
b1010 G
17
#550
07
#555
b1000 D
b1000 F
b1111111111111001 8
b1111111111111001 ?
b1111111111111001 ]
b1001 C
b1001 G
17
#560
07
#565
b111 D
b111 F
b1111111111111000 8
b1111111111111000 ?
b1111111111111000 ]
b1000 C
b1000 G
17
#570
07
#575
b110 D
b110 F
b1111111111110111 8
b1111111111110111 ?
b1111111111110111 ]
b111 C
b111 G
17
#580
07
#585
b101 D
b101 F
b1111111111110110 8
b1111111111110110 ?
b1111111111110110 ]
b110 C
b110 G
17
#590
07
#595
b100 D
b100 F
b1111111111110101 8
b1111111111110101 ?
b1111111111110101 ]
b101 C
b101 G
17
#600
07
#605
b11 D
b11 F
b1111111111110100 8
b1111111111110100 ?
b1111111111110100 ]
b100 C
b100 G
17
#610
07
#615
b10 D
b10 F
b1111111111110011 8
b1111111111110011 ?
b1111111111110011 ]
b11 C
b11 G
17
#620
07
#625
b1 D
b1 F
b1111111111110010 8
b1111111111110010 ?
b1111111111110010 ]
b10 C
b10 G
17
#630
07
#635
b0 D
b0 F
b1111111111110001 8
b1111111111110001 ?
b1111111111110001 ]
b1 C
b1 G
17
#640
07
#645
1E
b1111 D
b1111 F
b1111111111110000 8
b1111111111110000 ?
b1111111111110000 ]
b0 C
b0 G
17
#650
07
